<?xml-stylesheet href="/receta/recetas.xslt" type="text/xsl" ?>
<receta>
        <titulo>Flan de huevo</titulo>
        <fecha>11 de octubre de 2017</fecha>
        <introduccion>Este postre es una deliciosa opción para cualquier ocasión, suave y cremoso.</introduccion>
        <ingredientes>
            <ingrediente>6 huevos</ingrediente>
            <ingrediente>1 lata de leche condensada</ingrediente>
            <ingrediente>1 lata de leche evaporada</ingrediente>
            <ingrediente>1 taza de azúcar</ingrediente>
            <ingrediente>1 cucharadita de esencia de vainilla</ingrediente>
        </ingredientes>
        <preparacion>
            <p>1. Precalentar el horno a 180°C.</p>
            <p>2. En una olla, poner el azúcar y dejar que se derrita hasta formar un caramelo dorado.</p>
            <p>3. Verter el caramelo en un molde para flan y extenderlo por toda la superficie del molde.</p>
            <p>4. Batir los huevos en un tazón hasta que estén bien mezclados.</p>
            <p>5. Agregar la leche condensada, la leche evaporada y la esencia de vainilla, y mezclar bien.</p>
            <p>6. Verter la mezcla en el molde con el caramelo.</p>
            <p>7. Llevar al horno a baño maría durante 50 minutos o hasta que el flan esté firme.</p>
            <p>8. Dejar enfriar y desmoldar.</p>
            <p>9. Servir frío.</p>
        </preparacion>
</receta>